eis_sigmatools-0.23.1.data/data/etc/sigma/ala-azure-activitylogs.yml
eis_sigmatools-0.23.1.data/data/etc/sigma/ala-azure-ad_auditlogs.yml
eis_sigmatools-0.23.1.data/data/etc/sigma/ala-azure-aws_cloudtrail.yml
eis_sigmatools-0.23.1.data/data/etc/sigma/ala-suricata.yml
eis_sigmatools-0.23.1.data/data/etc/sigma/ala.yml
eis_sigmatools-0.23.1.data/data/etc/sigma/arcsight-zeek.yml
eis_sigmatools-0.23.1.data/data/etc/sigma/arcsight.yml
eis_sigmatools-0.23.1.data/data/etc/sigma/athena.yml
eis_sigmatools-0.23.1.data/data/etc/sigma/carbon-black-eedr.yml
eis_sigmatools-0.23.1.data/data/etc/sigma/carbon-black.yml
eis_sigmatools-0.23.1.data/data/etc/sigma/chronicle.yml
eis_sigmatools-0.23.1.data/data/etc/sigma/crowdstrike.yml
eis_sigmatools-0.23.1.data/data/etc/sigma/datadog.yml
eis_sigmatools-0.23.1.data/data/etc/sigma/devo-network.yml
eis_sigmatools-0.23.1.data/data/etc/sigma/devo-web.yml
eis_sigmatools-0.23.1.data/data/etc/sigma/devo-windows.yml
eis_sigmatools-0.23.1.data/data/etc/sigma/dnif.yml
eis_sigmatools-0.23.1.data/data/etc/sigma/ecs-auditbeat-modules-enabled.yml
eis_sigmatools-0.23.1.data/data/etc/sigma/ecs-auditd.yml
eis_sigmatools-0.23.1.data/data/etc/sigma/ecs-azure-activitylogs.yml
eis_sigmatools-0.23.1.data/data/etc/sigma/ecs-azure-ad_auditlogs.yml
eis_sigmatools-0.23.1.data/data/etc/sigma/ecs-azure-ad_signinlogs.yml
eis_sigmatools-0.23.1.data/data/etc/sigma/ecs-cloudtrail.yml
eis_sigmatools-0.23.1.data/data/etc/sigma/ecs-dns.yml
eis_sigmatools-0.23.1.data/data/etc/sigma/ecs-filebeat.yml
eis_sigmatools-0.23.1.data/data/etc/sigma/ecs-ms365_defender.yml
eis_sigmatools-0.23.1.data/data/etc/sigma/ecs-okta.yml
eis_sigmatools-0.23.1.data/data/etc/sigma/ecs-proxy.yml
eis_sigmatools-0.23.1.data/data/etc/sigma/ecs-suricata.yml
eis_sigmatools-0.23.1.data/data/etc/sigma/ecs-zeek-corelight.yml
eis_sigmatools-0.23.1.data/data/etc/sigma/ecs-zeek-elastic-beats-implementation.yml
eis_sigmatools-0.23.1.data/data/etc/sigma/elk-defaultindex-filebeat.yml
eis_sigmatools-0.23.1.dist-info/METADATA
eis_sigmatools-0.23.1.dist-info/WHEEL
eis_sigmatools-0.23.1.dist-info/entry_points.txt
eis_sigmatools-0.23.1.dist-info/top_level.txt
eis_sigmatools-0.23.1.dist-info/RECORD
